launchctl_py/__init__.py
launchctl_py/cli.py
launchctl_py/create.py
launchctl_py/status.py
launchctl_py-0.1.2.dist-info/entry_points.txt
launchctl_py-0.1.2.dist-info/WHEEL
launchctl_py-0.1.2.dist-info/METADATA
launchctl_py-0.1.2.dist-info/RECORD
