Metadata-Version: 2.1
Name: launchctl-py
Version: 0.1.2
Summary: Quickly create simple background services (i.e., launchctl agents) for macOS.
License: MIT
Author: Alyetama
Author-email: malyetama@pm.me
Requires-Python: >=3.7,<4.0
Classifier: License :: OSI Approved :: MIT License
Classifier: Programming Language :: Python :: 3
Classifier: Programming Language :: Python :: 3.10
Classifier: Programming Language :: Python :: 3.7
Classifier: Programming Language :: Python :: 3.8
Classifier: Programming Language :: Python :: 3.9
Requires-Dist: tabulate (>=0.8.9)
